.DS_Store
easycolab/__init__.py
easycolab/easycolab.py
easycolab-0.1b29.dist-info/DESCRIPTION.rst
easycolab-0.1b29.dist-info/METADATA
easycolab-0.1b29.dist-info/RECORD
easycolab-0.1b29.dist-info/WHEEL
easycolab-0.1b29.dist-info/metadata.json
easycolab-0.1b29.dist-info/top_level.txt
