Metadata-Version: 2.0
Name: easycolab
Version: 0.1b29
Summary: EasyColab: Easy access to the most used methods on Google Colab
Home-page: https://github.com/wittmannf/easycolab/
Author: Fernando Marcos Wittmann
Author-email: fernando.wittmann@gmail.com
License: MIT
Keywords: easycolab
Platform: UNKNOWN
Classifier: Development Status :: 4 - Beta
Classifier: Intended Audience :: Science/Research
Classifier: License :: OSI Approved :: MIT License
Classifier: Natural Language :: English
Classifier: Programming Language :: Python :: 2
Classifier: Programming Language :: Python :: 2.7
Classifier: Programming Language :: Python :: 3
Classifier: Programming Language :: Python :: 3.4
Classifier: Programming Language :: Python :: 3.5
Classifier: Programming Language :: Python :: 3.6
